ds_emer/Funciones.py
ds_emer/__init__.py
ds_emer-0.0.2.dist-info/METADATA
ds_emer-0.0.2.dist-info/WHEEL
ds_emer-0.0.2.dist-info/top_level.txt
ds_emer-0.0.2.dist-info/RECORD
