Metadata-Version: 2.1
Name: ds-emer
Version: 0.0.2
Summary: Librería de prueba para DS Emergencias
Home-page: https://github.com/IHSA-frio
Author: Facundo Rio
Author-email: frio@emergencias.com.ar
License: MIT
Platform: UNKNOWN
